{
  "annotations": {
    "list": [
      {
        "builtIn": 1,
        "datasource": {
          "type": "grafana",
          "uid": "-- Grafana --"
        },
        "enable": true,
        "hide": true,
        "iconColor": "rgba(0, 211, 255, 1)",
        "name": "Annotations & Alerts",
        "type": "dashboard"
      }
    ]
  },
  "editable": true,
  "fiscalYearStartMonth": 0,
  "graphTooltip": 0,
  "id": 1,
  "links": [],
  "panels": [
    {
      "datasource": {
        "type": "prometheus",
        "uid": "aewqukh8d7ke8f"
      },
      "fieldConfig": {
        "defaults": {
          "color": {
            "mode": "palette-classic"
          },
          "custom": {
            "axisBorderShow": false,
            "axisCenteredZero": false,
            "axisColorMode": "text",
            "axisLabel": "",
            "axisPlacement": "auto",
            "barAlignment": 0,
            "barWidthFactor": 0.6,
            "drawStyle": "line",
            "fillOpacity": 0,
            "gradientMode": "none",
            "hideFrom": {
              "legend": false,
              "tooltip": false,
              "viz": false
            },
            "insertNulls": false,
            "lineInterpolation": "linear",
            "lineWidth": 1,
            "pointSize": 5,
            "scaleDistribution": {
              "type": "linear"
            },
            "showPoints": "auto",
            "spanNulls": false,
            "stacking": {
              "group": "A",
              "mode": "none"
            },
            "thresholdsStyle": {
              "mode": "off"
            }
          },
          "mappings": [],
          "thresholds": {
            "mode": "absolute",
            "steps": [
              {
                "color": "green",
                "value": 0
              },
              {
                "color": "red",
                "value": 80
              }
            ]
          }
        },
        "overrides": [
          {
            "__systemRef": "hideSeriesFrom",
            "matcher": {
              "id": "byNames",
              "options": {
                "mode": "exclude",
                "names": [
                  "sum(rate(http_requests_total[1m]))"
                ],
                "prefix": "All except:",
                "readOnly": true
              }
            },
            "properties": [
              {
                "id": "custom.hideFrom",
                "value": {
                  "legend": false,
                  "tooltip": false,
                  "viz": true
                }
              }
            ]
          }
        ]
      },
      "gridPos": {
        "h": 8,
        "w": 12,
        "x": 0,
        "y": 0
      },
      "id": 1,
      "options": {
        "legend": {
          "calcs": [],
          "displayMode": "list",
          "placement": "bottom",
          "showLegend": true
        },
        "tooltip": {
          "hideZeros": false,
          "mode": "single",
          "sort": "none"
        }
      },
      "pluginVersion": "12.1.1",
      "targets": [
        {
          "datasource": {
            "type": "prometheus",
            "uid": "aewqukh8d7ke8f"
          },
          "editorMode": "code",
          "expr": "sum(rate(http_requests_total[1m]))",
          "legendFormat": "__auto",
          "range": true,
          "refId": "A"
        }
      ],
      "title": "New panel",
      "type": "timeseries"
    }
  ],
  "preload": false,
  "schemaVersion": 41,
  "tags": [],
  "templating": {
    "list": []
  },
  "time": {
    "from": "now-6h",
    "to": "now"
  },
  "timepicker": {},
  "timezone": "browser",
  "title": "Flashapp  usedprometheus",
  "uid": "619dd43d-0641-4801-92b9-a73e8e19b588",
  "version": 2
}